i2nca/__init__.py
i2nca/main.py
i2nca/convtools/__init__.py
i2nca/convtools/combiner_tools.py
i2nca/convtools/conv_tools.py
i2nca/convtools/snippet_tools.py
i2nca/dependencies/ImzMLWriter.py
i2nca/dependencies/__init__.py
i2nca/dependencies/dependencies.py
i2nca/qctools/__init__.py
i2nca/qctools/qc_tools.py
i2nca/qctools/utils.py
i2nca/qctools/visualization.py
i2nca/tests/__init__.py
i2nca/tests/test_built.py
i2nca/tests/test_cli.py
i2nca/tests/test_combiner.py
i2nca/tests/test_conv_cp.py
i2nca/tests/test_conv_pc.py
i2nca/tests/test_conv_pp.py
i2nca/tests/test_cutter.py
i2nca/tests/test_qc.py
i2nca/workflows/__init__.py
i2nca/workflows/cli/__init__.py
i2nca/workflows/cli/agnostic_qc_cli.py
i2nca/workflows/cli/calibrant_qc_cli.py
i2nca/workflows/cli/file_joiner_cli.py
i2nca/workflows/cli/file_splitter_cli.py
i2nca/workflows/cli/pc_2_cc_cli.py
i2nca/workflows/cli/pp_2_cp_cli.py
i2nca/workflows/cli/profile_2_centroid_cli.py
i2nca/workflows/cli/region_qc_cli.py
i2nca-0.3.12.dist-info/COPYING
i2nca-0.3.12.dist-info/METADATA
i2nca-0.3.12.dist-info/WHEEL
i2nca-0.3.12.dist-info/entry_points.txt
i2nca-0.3.12.dist-info/top_level.txt
i2nca-0.3.12.dist-info/RECORD
