Metadata-Version: 2.1
Name: i2nca
Version: 0.3.12
Summary: A MSI workflow package for top-level use and introduction of data preprocessing into workflow engines
Author: Jannik Witte
License: GNU GENERAL PUBLIC LICENSE
Project-URL: Homepage, https://github.com/cKNUSPeR/i2nca
Project-URL: Issues, https://github.com/cKNUSPeR/i2nca/issues
Classifier: Programming Language :: Python :: 3
Classifier: License :: OSI Approved :: GNU General Public License v3 (GPLv3)
Classifier: Operating System :: OS Independent
Requires-Python: >=3.10
License-File: COPYING
Requires-Dist: numpy <2,>=1.24
Requires-Dist: pandas >=2.1
Requires-Dist: matplotlib <3.9,==3.7
Requires-Dist: scipy >=1.12
Requires-Dist: m2aia >=0.5
Requires-Dist: pyimzml >=1.5
